{
    "clientID":"18",
    "almondMAC":"251176215905264",
    "clientMAC":"14:30:c6:46:b7:15",
    "Data": [
             {
             "Date":"2016/07/14",
             "URIs":[
                     {
                     "key":"26",
                     "Hostname":"www.twitter.com",
                     "Epoch":1468494200,
                     "Count":60
                     },
                     {
                     "key":"25",
                     "Hostname":"www.facebook.com",
                     "Epoch":1468493266,
                     "Count":60
                     },
                     {
                     "key":"24",
                     "Hostname":"www.google.com",
                     "Epoch":1468493066,
                     "Count":3
                     },
                     {
                     "key":"23",
                     "Hostname":"www.gmail.com",
                     "Epoch":1468470000,
                     "Count":10
                     },
                     {
                     "key":"22",
                     "Hostname":"www.skype.com",
                     "Epoch":1468468066,
                     "Count":3
                     },
                     {
                     "key":"21",
                     "Hostname":"www.quora.com",
                     "Epoch":1468460000,
                     "Count":10
                     }
                     ]
             },
             {
             "Date":"2016/07/13",
             "URIs":[
                     {
                     "key":"20",
                     "Hostname":"www.google.com",
                     "Epoch":1468389600,
                     "Count":60
                     },
                     {
                     "key":"19",
                     "Hostname":"www.gmail.com",
                     "Epoch":1468386999,
                     "Count":60
                     },
                     {
                     "key":"18",
                     "Hostname":"www.tv9.com",
                     "Epoch":1468386760,
                     "Count":3
                     },
                     {
                     "key":"17",
                     "Hostname":"www.ndtv.com",
                     "Epoch":1468386600,
                     "Count":10
                     }
                     ]
             },
             {
             "Date":"2016/07/12",
             "URIs":[
                     {
                     "key":"16",
                     "Hostname":"www.gmail.com",
                     "Epoch":1468318200,
                     "Count":60
                     },
                     {
                     "key":"15",
                     "Hostname":"www.facebook.com",
                     "Epoch":1468307200,
                     "Count":60
                     },
                     {
                     "key":"14",
                     "Hostname":"www.skype.com",
                     "Epoch":1468306200,
                     "Count":3
                     },
                     {
                     "key":"13",
                     "Hostname":"www.ndtv.com",
                     "Epoch":1468300200,
                     "Count":10
                     }
                     ]
             },
             {
             "Date":"2016/07/11",
             "URIs":[ {
                     "key":"12",
                     "Hostname":"www.gmail.com",
                     "Epoch":1468239600,
                     "Count":60
                     },
                     {
                     "key":"11",
                     "Hostname":"www.google.com",
                     "Epoch":1468235600,
                     "Count":3
                     },
                     {
                     "key":"10",
                     "Hostname":"www.twitter.com",
                     "Epoch":1468230600,
                     "Count":10
                     }
                     ]
             },
             {
             "Date":"2016/07/10",
             "URIs":[
                     {
                     "key":"9",
                     "Hostname":"www.facebook.com",
                     "Epoch":1468154700,
                     "Count":60
                     },
                     {
                     "key":"8",
                     "Hostname":"www.gmail.com",
                     "Epoch":1468150700,
                     "Count":3
                     },
                     {
                     "key":"7",
                     "Hostname":"www.quora.com",
                     "Epoch":1468145000,
                     "Count":10
                     }
                     ]
             },
             {
             "Date":"2016/07/01",
             "URIs":[
                     {
                     "key":"6",
                     "Hostname":"www.facebook.com",
                     "Epoch":1467377100,
                     "Count":60
                     },
                     {
                     "key":"5",
                     "Hostname":"www.gmail.com",
                     "Epoch":1467370100,
                     "Count":3
                     },
                     {
                     "key":"4",
                     "Hostname":"www.quora.com",
                     "Epoch":1467369100,
                     "Count":10
                     }
                     ]
             },
             {
             "Date":"2016/06/14",
             "URIs":[
                     {
                     "key":"3",
                     "Hostname":"www.facebook.com",
                     "Epoch":1465891638,
                     "Count":60
                     },
                     {
                     "key":"2",
                     "Hostname":"www.gmail.com",
                     "Epoch":1465885638,
                     "Count":3
                     },
                     {
                     "key":"1",
                     "Hostname":"www.quora.com",
                     "Epoch":1465881638,
                     "Count":10
                     }
                     ]
             }
             ]
}